create_subject/__init__.py
create_subject/create_subject.py
create_subject-0.0.4.dist-info/METADATA
create_subject-0.0.4.dist-info/RECORD
create_subject-0.0.4.dist-info/WHEEL
create_subject-0.0.4.dist-info/top_level.txt
